bugbountycrawler/__init__.py
bugbountycrawler/api/__init__.py
bugbountycrawler/api/app.py
bugbountycrawler/api/routers/__init__.py
bugbountycrawler/api/routers/findings.py
bugbountycrawler/api/routers/metrics.py
bugbountycrawler/api/routers/programs.py
bugbountycrawler/api/routers/scans.py
bugbountycrawler/api/routers/targets.py
bugbountycrawler/api/routers/users.py
bugbountycrawler/cli/__init__.py
bugbountycrawler/cli/app.py
bugbountycrawler/cli/commands/__init__.py
bugbountycrawler/cli/commands/create_program.py
bugbountycrawler/cli/commands/create_user.py
bugbountycrawler/cli/commands/init_db.py
bugbountycrawler/cli/commands/list_programs.py
bugbountycrawler/cli/commands/scan.py
bugbountycrawler/cli/commands/web_ui.py
bugbountycrawler/core/__init__.py
bugbountycrawler/core/anomaly_detector.py
bugbountycrawler/core/config.py
bugbountycrawler/core/false_positive_reducer.py
bugbountycrawler/core/logger.py
bugbountycrawler/core/metrics_tracker.py
bugbountycrawler/core/ml_assistant.py
bugbountycrawler/core/rate_limiter.py
bugbountycrawler/core/scope.py
bugbountycrawler/crawlers/__init__.py
bugbountycrawler/crawlers/base.py
bugbountycrawler/crawlers/manager.py
bugbountycrawler/crawlers/spa_crawler.py
bugbountycrawler/crawlers/web_crawler.py
bugbountycrawler/database/__init__.py
bugbountycrawler/database/connection.py
bugbountycrawler/database/models.py
bugbountycrawler/models/__init__.py
bugbountycrawler/models/finding.py
bugbountycrawler/models/program.py
bugbountycrawler/models/scan.py
bugbountycrawler/models/target.py
bugbountycrawler/models/user.py
bugbountycrawler/plugins/__init__.py
bugbountycrawler/plugins/base.py
bugbountycrawler/plugins/manager.py
bugbountycrawler/plugins/sandbox.py
bugbountycrawler/scanners/__init__.py
bugbountycrawler/scanners/api_security.py
bugbountycrawler/scanners/asset_discovery.py
bugbountycrawler/scanners/authentication.py
bugbountycrawler/scanners/base.py
bugbountycrawler/scanners/business_logic.py
bugbountycrawler-1.0.0.dist-info/METADATA
bugbountycrawler-1.0.0.dist-info/WHEEL
bugbountycrawler-1.0.0.dist-info/entry_points.txt
bugbountycrawler-1.0.0.dist-info/top_level.txt
bugbountycrawler-1.0.0.dist-info/RECORD
