Metadata-Version: 2.4
Name: bugbountycrawler
Version: 1.0.0
Summary: A production-ready, legal, modular BugBountyCrawler for ethical bug bounty hunting
Home-page: https://github.com/yourusername/bugbountycrawler
Author: BugBountyCrawler Team
Author-email: BugBountyCrawler Team <team@bugbountycrawler.dev>
License: MIT
Classifier: Development Status :: 5 - Production/Stable
Classifier: Intended Audience :: Information Technology
Classifier: License :: OSI Approved :: MIT License
Classifier: Operating System :: OS Independent
Classifier: Programming Language :: Python :: 3
Classifier: Programming Language :: Python :: 3.11
Classifier: Programming Language :: Python :: 3.12
Classifier: Topic :: Security
Classifier: Topic :: Internet :: WWW/HTTP :: Indexing/Search
Requires-Python: >=3.11
Dynamic: author
Dynamic: home-page
Dynamic: requires-python
